<annotation>
	<folder>raw_frames</folder>
	<filename>allied_ai2_allied_ai2_000227.jpg</filename>
	<path>M:\ra3_bot\data\datasets\ra3_unified\raw_frames\allied_ai2_allied_ai2_000227.jpg</path>
	<source>
		<database>Unknown</database>
	</source>
	<size>
		<width>1920</width>
		<height>1080</height>
		<depth>3</depth>
	</size>
	<segmented>0</segmented>
	<object>
		<name>AlliedRefinery</name>
		<pose>Unspecified</pose>
		<truncated>0</truncated>
		<difficult>0</difficult>
		<bndbox>
			<xmin>589</xmin>
			<ymin>306</ymin>
			<xmax>1013</xmax>
			<ymax>695</ymax>
		</bndbox>
	</object>
	<object>
		<name>AlliedPowerPlant</name>
		<pose>Unspecified</pose>
		<truncated>0</truncated>
		<difficult>0</difficult>
		<bndbox>
			<xmin>1250</xmin>
			<ymin>467</ymin>
			<xmax>1490</xmax>
			<ymax>756</ymax>
		</bndbox>
	</object>
	<object>
		<name>AlliedPowerPlant</name>
		<pose>Unspecified</pose>
		<truncated>0</truncated>
		<difficult>0</difficult>
		<bndbox>
			<xmin>1391</xmin>
			<ymin>614</ymin>
			<xmax>1654</xmax>
			<ymax>964</ymax>
		</bndbox>
	</object>
	<object>
		<name>AlliedPowerPlant</name>
		<pose>Unspecified</pose>
		<truncated>0</truncated>
		<difficult>0</difficult>
		<bndbox>
			<xmin>35</xmin>
			<ymin>127</ymin>
			<xmax>284</xmax>
			<ymax>324</ymax>
		</bndbox>
	</object>
	<object>
		<name>AlliedPowerPlant</name>
		<pose>Unspecified</pose>
		<truncated>1</truncated>
		<difficult>0</difficult>
		<bndbox>
			<xmin>1</xmin>
			<ymin>382</ymin>
			<xmax>275</xmax>
			<ymax>627</ymax>
		</bndbox>
	</object>
	<object>
		<name>AlliedWarFactory</name>
		<pose>Unspecified</pose>
		<truncated>0</truncated>
		<difficult>0</difficult>
		<bndbox>
			<xmin>1245</xmin>
			<ymin>127</ymin>
			<xmax>1559</xmax>
			<ymax>425</ymax>
		</bndbox>
	</object>
	<object>
		<name>AlliedConstructionYard</name>
		<pose>Unspecified</pose>
		<truncated>0</truncated>
		<difficult>0</difficult>
		<bndbox>
			<xmin>779</xmin>
			<ymin>9</ymin>
			<xmax>1095</xmax>
			<ymax>336</ymax>
		</bndbox>
	</object>
	<object>
		<name>AlliedBarracks</name>
		<pose>Unspecified</pose>
		<truncated>0</truncated>
		<difficult>0</difficult>
		<bndbox>
			<xmin>1514</xmin>
			<ymin>406</ymin>
			<xmax>1830</xmax>
			<ymax>629</ymax>
		</bndbox>
	</object>
	<object>
		<name>AlliedAirfield</name>
		<pose>Unspecified</pose>
		<truncated>0</truncated>
		<difficult>0</difficult>
		<bndbox>
			<xmin>189</xmin>
			<ymin>44</ymin>
			<xmax>670</xmax>
			<ymax>276</ymax>
		</bndbox>
	</object>
	<object>
		<name>AlliedAirfield</name>
		<pose>Unspecified</pose>
		<truncated>1</truncated>
		<difficult>0</difficult>
		<bndbox>
			<xmin>1146</xmin>
			<ymin>1</ymin>
			<xmax>1560</xmax>
			<ymax>140</ymax>
		</bndbox>
	</object>
	<object>
		<name>AlliedBaseDefense</name>
		<pose>Unspecified</pose>
		<truncated>0</truncated>
		<difficult>0</difficult>
		<bndbox>
			<xmin>1258</xmin>
			<ymin>726</ymin>
			<xmax>1383</xmax>
			<ymax>872</ymax>
		</bndbox>
	</object>
	<object>
		<name>AlliedBaseDefense</name>
		<pose>Unspecified</pose>
		<truncated>0</truncated>
		<difficult>0</difficult>
		<bndbox>
			<xmin>1726</xmin>
			<ymin>404</ymin>
			<xmax>1795</xmax>
			<ymax>462</ymax>
		</bndbox>
	</object>
</annotation>