<annotation>
	<folder>raw_frames</folder>
	<filename>soviet_ffa_20260430_074959_000082.jpg</filename>
	<path>M:\ra3_bot\data\datasets\ra3_unified\raw_frames\soviet_ffa_20260430_074959_000082.jpg</path>
	<source>
		<database>Unknown</database>
	</source>
	<size>
		<width>1920</width>
		<height>1080</height>
		<depth>3</depth>
	</size>
	<segmented>0</segmented>
	<object>
		<name>SovietPowerPlant</name>
		<pose>Unspecified</pose>
		<truncated>1</truncated>
		<difficult>0</difficult>
		<bndbox>
			<xmin>448</xmin>
			<ymin>1</ymin>
			<xmax>555</xmax>
			<ymax>47</ymax>
		</bndbox>
	</object>
	<object>
		<name>SovietConstructionYard</name>
		<pose>Unspecified</pose>
		<truncated>0</truncated>
		<difficult>0</difficult>
		<bndbox>
			<xmin>894</xmin>
			<ymin>90</ymin>
			<xmax>1109</xmax>
			<ymax>277</ymax>
		</bndbox>
	</object>
	<object>
		<name>SovietRefinery</name>
		<pose>Unspecified</pose>
		<truncated>0</truncated>
		<difficult>0</difficult>
		<bndbox>
			<xmin>373</xmin>
			<ymin>190</ymin>
			<xmax>628</xmax>
			<ymax>370</ymax>
		</bndbox>
	</object>
	<object>
		<name>SovietWarFactory</name>
		<pose>Unspecified</pose>
		<truncated>1</truncated>
		<difficult>0</difficult>
		<bndbox>
			<xmin>1279</xmin>
			<ymin>1</ymin>
			<xmax>1500</xmax>
			<ymax>156</ymax>
		</bndbox>
	</object>
	<object>
		<name>SovietBarracks</name>
		<pose>Unspecified</pose>
		<truncated>0</truncated>
		<difficult>0</difficult>
		<bndbox>
			<xmin>830</xmin>
			<ymin>471</ymin>
			<xmax>1055</xmax>
			<ymax>725</ymax>
		</bndbox>
	</object>
	<object>
		<name>SovietBaseDefense</name>
		<pose>Unspecified</pose>
		<truncated>0</truncated>
		<difficult>0</difficult>
		<bndbox>
			<xmin>394</xmin>
			<ymin>44</ymin>
			<xmax>459</xmax>
			<ymax>95</ymax>
		</bndbox>
	</object>
</annotation>