<annotation>
	<folder>raw_frames</folder>
	<filename>soviet_ffa_20260430_074959_000316.jpg</filename>
	<path>M:\ra3_bot\data\datasets\ra3_unified\raw_frames\soviet_ffa_20260430_074959_000316.jpg</path>
	<source>
		<database>Unknown</database>
	</source>
	<size>
		<width>1920</width>
		<height>1080</height>
		<depth>3</depth>
	</size>
	<segmented>0</segmented>
	<object>
		<name>SovietPowerPlant</name>
		<pose>Unspecified</pose>
		<truncated>0</truncated>
		<difficult>0</difficult>
		<bndbox>
			<xmin>786</xmin>
			<ymin>307</ymin>
			<xmax>889</xmax>
			<ymax>389</ymax>
		</bndbox>
	</object>
	<object>
		<name>SovietPowerPlant</name>
		<pose>Unspecified</pose>
		<truncated>0</truncated>
		<difficult>0</difficult>
		<bndbox>
			<xmin>1001</xmin>
			<ymin>196</ymin>
			<xmax>1090</xmax>
			<ymax>259</ymax>
		</bndbox>
	</object>
	<object>
		<name>SovietConstructionYard</name>
		<pose>Unspecified</pose>
		<truncated>0</truncated>
		<difficult>0</difficult>
		<bndbox>
			<xmin>15</xmin>
			<ymin>470</ymin>
			<xmax>250</xmax>
			<ymax>716</ymax>
		</bndbox>
	</object>
	<object>
		<name>SovietRefinery</name>
		<pose>Unspecified</pose>
		<truncated>0</truncated>
		<difficult>0</difficult>
		<bndbox>
			<xmin>329</xmin>
			<ymin>16</ymin>
			<xmax>516</xmax>
			<ymax>166</ymax>
		</bndbox>
	</object>
</annotation>